{
    "1": {
        "name" : "Silverkeep",
        "connections" : [],
        "npc" : [],
        "traveltime": 25
    },
    "2": {
        "name" : "Dsian's House",
        "connections" : [],
        "npc" : [],
        "traveltime": 10
    },
    "3": {
        "name" : "Mournstead",
        "connections" : [],
        "npc" : [],
        "traveltime": 30
    },
    "4": {
        "name" : "Rivermouth",
        "connections" : [3, 44],
        "npc" : [],
        "traveltime": 30
    },
    "5": {
        "name" : "Temple of MOUKN",
        "connections" : [],
        "npc" : [],
        "traveltime": 60
    },
    "6": {
        "name" : "Copperfall",
        "connections" : [],
        "npc" : [],
        "traveltime": 40
    },
    "7": {
        "name" : "Copperfall Swamp",
        "connections" : [],
        "npc" : [],
        "traveltime": 30
    },
    "8":{},
    "9":{},
    "10":{},
    "11": {
        "name" : "Ravengate",
        "connections" : [],
        "npc" : [],
        "traveltime": 40
    },
    "12":{},
    "13": {
        "name" : "Copperfall Summit",
        "connections" : [],
        "npc" : [],
        "traveltime": 100
    },
    "14": {
        "name" : "Redhorn",
        "connections" : [44],
        "npc" : [],
        "traveltime": 15
    },
    "15":{},
    "16": {
        "name" : "Frostridge Shore",
        "connections" : [4],
        "npc" : [],
        "traveltime": 300
    },
    "17": {
        "name" : "Frostridge",
        "connections" : [],
        "npc" : [],
        "traveltime": 32
    },
    "18": {
        "name" : "Blackburn Mountain",
        "connections" : [],
        "npc" : [],
        "traveltime": 30
    },
    "19": {
        "name" : "Mirror Isle",
        "connections" : [],
        "npc" : [],
        "traveltime": 20
    },
    "20": {
        "name" : "Sariila",
        "connections" : [4],
        "npc" : [],
        "traveltime": 250
    },
    "21": {
        "name" : "Miree",
        "connections" : [],
        "npc" : [],
        "traveltime": 23
    },
    "22": {
        "name" : "Dingerou Cavern",
        "connections" : [],
        "npc" : [],
        "traveltime": 15
    },
    "23": {},
    "24": {},
    "25": {
        "name" : "Bazaar of Lights",
        "connections" : [],
        "npc" : [],
        "traveltime": 20
    },
    "26": {
        "name" : "Silverkeep Altar",
        "connections" : [],
        "npc" : [],
        "traveltime": 5
    },
    "27": {
        "name" : "Frostridge Tavern",
        "connections" : [],
        "npc" : [],
        "traveltime": 5
    },
    "28":{},
    "29":{},
    "30": {
        "name" : "Scorched Desert",
        "connections" : [],
        "npc" : [],
        "traveltime": 15
    },
    "31": {
        "name" : "Sandy Tomb",
        "connections" : [],
        "npc" : [],
        "traveltime": 15
    },
    "32": {
        "name" : "Tower of Eternity",
        "connections" : [],
        "npc" : [],
        "traveltime": 120
    },
    "33": {
        "name" : "Buckleport",
        "connections" : [],
        "npc" : [],
        "traveltime": 120
    },
    "34": {
        "name" : "Ashgate",
        "connections" : [],
        "npc" : [],
        "traveltime": 10
    },
    "35": {
        "name" : "Lemontree Plaza",
        "connections" : [],
        "npc" : [],
        "traveltime": 10
    },
    "36": {
        "name" : "Bibliothecam Magnum",
        "connections" : [],
        "npc" : [],
        "traveltime": 10
    },
    "37": {
        "name" : "Sanctum of Serenity",
        "connections" : [],
        "npc" : [],
        "traveltime": 10
    },
    "38": {
        "name" : "The Sick Dahlia",
        "connections" : [],
        "npc" : [],
        "traveltime": 10
    },
    "39": {
        "name" : "Maple Grove",
        "connections" : [],
        "npc" : [],
        "traveltime": 10
    },
    "40": {
        "name" : "Dawnburg",
        "connections" : [],
        "npc" : [],
        "traveltime": 10
    },
    "41": {
        "name" : "Copperfall Altar",
        "connections" : [],
        "npc" : [],
        "traveltime": 20
    },
    "42":{},
    "43": {
        "name" : "Sariila Altar",
        "connections" : [],
        "npc" : [],
        "traveltime": 10
    },
    "44": {
        "name" : "Redhorn Dungeon",
        "connections" : [14],
        "npc" : [],
        "traveltime": 15
    },
    "45": {
        "name" : "Nightmare's Heaven",
        "connections" : [35],
        "npc" : ["Nightmare", "Jesie"],
        "traveltime": 10
    }
}